{
  "schema_version": "1.1",
  "object_name": "HVTIRoI_P_75200434_P_0A273D3B_TRUSTPATH_070726155032.JSON",
  "WindowsSafeFileName": "R_M_71F183602DB1.JSON",
  "OriginalRequestedFileName": "HVTIRoI_P_75200434_P_0A273D3B_TRUSTPATH_070726155032.JSON",
  "PersonAID": "P_75200434",
  "PersonBID": "P_0A273D3B",
  "PersonAName": "George Spencer 038",
  "PersonBName": "Michael Evans 071",
  "BVHID": "BVH_95CCE7DB8D",
  "BVHTypeID": "TRUSTPATH",
  "BVHTypeName": "TRUSTPATH",
  "PairMatchScore": 82.8,
  "BVHTypeFitScore": 82.78,
  "ValueScore": 84.61,
  "RankingScore": 80.22,
  "EstimatedHVITUSDValue": 836295,
  "EstimatedExpectedUSDValue": 421493,
  "EstimatedHVITUSDValue Explainer": "Estimated potential value uses relationship_acceleration_value_proxy. Profile signals considered: PersonA product/value case $965,200, PersonB product/value case $3,345,180, buyer pain/cost signals $1,988,636. Selected potential value is $836,295; expected value is $421,493 after applying 50.4% estimated transaction probability.",
  "RoIModelMethod": "relationship_acceleration_value_proxy",
  "Currency": "USD",
  "GBPToUSD": 1.27,
  "ValueSignals": {
    "PersonAProductOrValueCaseUSD": 965200,
    "PersonBProductOrValueCaseUSD": 3345180,
    "PersonABuyerPainUSD": 1235610,
    "PersonBBuyerPainUSD": 1988636
  }
}